super_rockket/__init__.py
super_rockket/super_rockket.py
super_rockket-1.0.0.dist-info/LICENSE.txt
super_rockket-1.0.0.dist-info/METADATA
super_rockket-1.0.0.dist-info/WHEEL
super_rockket-1.0.0.dist-info/top_level.txt
super_rockket-1.0.0.dist-info/RECORD
